[
{"cate_url": "https://finance.naver.com/sise/sise_group_detail.naver?type=upjong&no=286", "cate_name": "생물공학", "vart_rate": "8.43%", "stck_cnt": 49, "incr_cnt": 48, "flat_cnt": 0, "desc_cnt": 1},
{"cate_url": "https://finance.naver.com/sise/sise_group_detail.naver?type=upjong&no=262", "cate_name": "생명과학도구및서비스", "vart_rate": "7.98%", "stck_cnt": 31, "incr_cnt": 28, "flat_cnt": 2, "desc_cnt": 1},
{"cate_url": "https://finance.naver.com/sise/sise_group_detail.naver?type=upjong&no=300", "cate_name": "양방향미디어와서비스", "vart_rate": "6.37%", "stck_cnt": 11, "incr_cnt": 11, "flat_cnt": 0, "desc_cnt": 0},
{"cate_url": "https://finance.naver.com/sise/sise_group_detail.naver?type=upjong&no=284", "cate_name": "우주항공과국방", "vart_rate": "6.09%", "stck_cnt": 16, "incr_cnt": 13, "flat_cnt": 2, "desc_cnt": 1},
{"cate_url": "https://finance.naver.com/sise/sise_group_detail.naver?type=upjong&no=285", "cate_name": "방송과엔터테인먼트", "vart_rate": "5.83%", "stck_cnt": 55, "incr_cnt": 48, "flat_cnt": 3, "desc_cnt": 4},
{"cate_url": "https://finance.naver.com/sise/sise_group_detail.naver?type=upjong&no=263", "cate_name": "게임엔터테인먼트", "vart_rate": "5.66%", "stck_cnt": 34, "incr_cnt": 29, "flat_cnt": 3, "desc_cnt": 2},
{"cate_url": "https://finance.naver.com/sise/sise_group_detail.naver?type=upjong&no=294", "cate_name": "통신장비", "vart_rate": "5.66%", "stck_cnt": 44, "incr_cnt": 42, "flat_cnt": 2, "desc_cnt": 0},
{"cate_url": "https://finance.naver.com/sise/sise_group_detail.naver?type=upjong&no=306", "cate_name": "전기장비", "vart_rate": "5.21%", "stck_cnt": 28, "incr_cnt": 27, "flat_cnt": 1, "desc_cnt": 0},
{"cate_url": "https://finance.naver.com/sise/sise_group_detail.naver?type=upjong&no=320", "cate_name": "건축제품", "vart_rate": "5.02%", "stck_cnt": 15, "incr_cnt": 15, "flat_cnt": 0, "desc_cnt": 0},
{"cate_url": "https://finance.naver.com/sise/sise_group_detail.naver?type=upjong&no=308", "cate_name": "인터넷과카탈로그소매", "vart_rate": "4.89%", "stck_cnt": 11, "incr_cnt": 10, "flat_cnt": 1, "desc_cnt": 0},
{"cate_url": "https://finance.naver.com/sise/sise_group_detail.naver?type=upjong&no=279", "cate_name": "건설", "vart_rate": "4.83%", "stck_cnt": 73, "incr_cnt": 70, "flat_cnt": 1, "desc_cnt": 2},
{"cate_url": "https://finance.naver.com/sise/sise_group_detail.naver?type=upjong&no=326", "cate_name": "항공화물운송과물류", "vart_rate": "4.73%", "stck_cnt": 13, "incr_cnt": 13, "flat_cnt": 0, "desc_cnt": 0},
{"cate_url": "https://finance.naver.com/sise/sise_group_detail.naver?type=upjong&no=316", "cate_name": "건강관리업체및서비스", "vart_rate": "4.69%", "stck_cnt": 4, "incr_cnt": 3, "flat_cnt": 0, "desc_cnt": 1},
{"cate_url": "https://finance.naver.com/sise/sise_group_detail.naver?type=upjong&no=281", "cate_name": "건강관리장비와용품", "vart_rate": "4.64%", "stck_cnt": 68, "incr_cnt": 59, "flat_cnt": 4, "desc_cnt": 5},
{"cate_url": "https://finance.naver.com/sise/sise_group_detail.naver?type=upjong&no=297", "cate_name": "가정용품", "vart_rate": "4.48%", "stck_cnt": 8, "incr_cnt": 8, "flat_cnt": 0, "desc_cnt": 0},
{"cate_url": "https://finance.naver.com/sise/sise_group_detail.naver?type=upjong&no=287", "cate_name": "소프트웨어", "vart_rate": "4.46%", "stck_cnt": 60, "incr_cnt": 56, "flat_cnt": 2, "desc_cnt": 2},
{"cate_url": "https://finance.naver.com/sise/sise_group_detail.naver?type=upjong&no=339", "cate_name": "다각화된소비자서비스", "vart_rate": "4.42%", "stck_cnt": 1, "incr_cnt": 1, "flat_cnt": 0, "desc_cnt": 0},
{"cate_url": "https://finance.naver.com/sise/sise_group_detail.naver?type=upjong&no=288", "cate_name": "건강관리기술", "vart_rate": "4.37%", "stck_cnt": 12, "incr_cnt": 11, "flat_cnt": 0, "desc_cnt": 1},
{"cate_url": "https://finance.naver.com/sise/sise_group_detail.naver?type=upjong&no=269", "cate_name": "디스플레이장비및부품", "vart_rate": "3.9%", "stck_cnt": 85, "incr_cnt": 73, "flat_cnt": 5, "desc_cnt": 7},
{"cate_url": "https://finance.naver.com/sise/sise_group_detail.naver?type=upjong&no=332", "cate_name": "문구류", "vart_rate": "3.78%", "stck_cnt": 2, "incr_cnt": 2, "flat_cnt": 0, "desc_cnt": 0},
{"cate_url": "https://finance.naver.com/sise/sise_group_detail.naver?type=upjong&no=299", "cate_name": "기계", "vart_rate": "3.72%", "stck_cnt": 95, "incr_cnt": 84, "flat_cnt": 6, "desc_cnt": 5},
{"cate_url": "https://finance.naver.com/sise/sise_group_detail.naver?type=upjong&no=277", "cate_name": "창업투자", "vart_rate": "3.72%", "stck_cnt": 87, "incr_cnt": 34, "flat_cnt": 17, "desc_cnt": 36},
{"cate_url": "https://finance.naver.com/sise/sise_group_detail.naver?type=upjong&no=313", "cate_name": "석유와가스", "vart_rate": "3.63%", "stck_cnt": 20, "incr_cnt": 19, "flat_cnt": 0, "desc_cnt": 1},
{"cate_url": "https://finance.naver.com/sise/sise_group_detail.naver?type=upjong&no=304", "cate_name": "철강", "vart_rate": "3.53%", "stck_cnt": 53, "incr_cnt": 51, "flat_cnt": 1, "desc_cnt": 1},
{"cate_url": "https://finance.naver.com/sise/sise_group_detail.naver?type=upjong&no=310", "cate_name": "광고", "vart_rate": "3.52%", "stck_cnt": 13, "incr_cnt": 13, "flat_cnt": 0, "desc_cnt": 0},
{"cate_url": "https://finance.naver.com/sise/sise_group_detail.naver?type=upjong&no=315", "cate_name": "손해보험", "vart_rate": "3.44%", "stck_cnt": 13, "incr_cnt": 10, "flat_cnt": 1, "desc_cnt": 2},
{"cate_url": "https://finance.naver.com/sise/sise_group_detail.naver?type=upjong&no=301", "cate_name": "은행", "vart_rate": "3.42%", "stck_cnt": 11, "incr_cnt": 11, "flat_cnt": 0, "desc_cnt": 0},
{"cate_url": "https://finance.naver.com/sise/sise_group_detail.naver?type=upjong&no=307", "cate_name": "전자제품", "vart_rate": "3.42%", "stck_cnt": 18, "incr_cnt": 17, "flat_cnt": 0, "desc_cnt": 1},
{"cate_url": "https://finance.naver.com/sise/sise_group_detail.naver?type=upjong&no=321", "cate_name": "증권", "vart_rate": "3.32%", "stck_cnt": 38, "incr_cnt": 35, "flat_cnt": 1, "desc_cnt": 2},
{"cate_url": "https://finance.naver.com/sise/sise_group_detail.naver?type=upjong&no=303", "cate_name": "가구", "vart_rate": "3.25%", "stck_cnt": 10, "incr_cnt": 9, "flat_cnt": 0, "desc_cnt": 1},
{"cate_url": "https://finance.naver.com/sise/sise_group_detail.naver?type=upjong&no=267", "cate_name": "IT서비스", "vart_rate": "3.21%", "stck_cnt": 77, "incr_cnt": 73, "flat_cnt": 3, "desc_cnt": 1},
{"cate_url": "https://finance.naver.com/sise/sise_group_detail.naver?type=upjong&no=328", "cate_name": "전문소매", "vart_rate": "3.21%", "stck_cnt": 6, "incr_cnt": 6, "flat_cnt": 0, "desc_cnt": 0},
{"cate_url": "https://finance.naver.com/sise/sise_group_detail.naver?type=upjong&no=274", "cate_name": "섬유,의류,신발,호화품", "vart_rate": "3.19%", "stck_cnt": 80, "incr_cnt": 73, "flat_cnt": 3, "desc_cnt": 4},
{"cate_url": "https://finance.naver.com/sise/sise_group_detail.naver?type=upjong&no=293", "cate_name": "컴퓨터와주변기기", "vart_rate": "3.17%", "stck_cnt": 24, "incr_cnt": 20, "flat_cnt": 3, "desc_cnt": 1},
{"cate_url": "https://finance.naver.com/sise/sise_group_detail.naver?type=upjong&no=292", "cate_name": "핸드셋", "vart_rate": "3.12%", "stck_cnt": 70, "incr_cnt": 58, "flat_cnt": 8, "desc_cnt": 4},
{"cate_url": "https://finance.naver.com/sise/sise_group_detail.naver?type=upjong&no=282", "cate_name": "전자장비와기기", "vart_rate": "2.97%", "stck_cnt": 93, "incr_cnt": 79, "flat_cnt": 5, "desc_cnt": 9},
{"cate_url": "https://finance.naver.com/sise/sise_group_detail.naver?type=upjong&no=266", "cate_name": "화장품", "vart_rate": "2.95%", "stck_cnt": 54, "incr_cnt": 49, "flat_cnt": 2, "desc_cnt": 3},
{"cate_url": "https://finance.naver.com/sise/sise_group_detail.naver?type=upjong&no=289", "cate_name": "건축자재", "vart_rate": "2.88%", "stck_cnt": 44, "incr_cnt": 40, "flat_cnt": 2, "desc_cnt": 2},
{"cate_url": "https://finance.naver.com/sise/sise_group_detail.naver?type=upjong&no=311", "cate_name": "포장재", "vart_rate": "2.85%", "stck_cnt": 28, "incr_cnt": 23, "flat_cnt": 4, "desc_cnt": 1},
{"cate_url": "https://finance.naver.com/sise/sise_group_detail.naver?type=upjong&no=268", "cate_name": "식품", "vart_rate": "2.85%", "stck_cnt": 90, "incr_cnt": 82, "flat_cnt": 3, "desc_cnt": 5},
{"cate_url": "https://finance.naver.com/sise/sise_group_detail.naver?type=upjong&no=314", "cate_name": "출판", "vart_rate": "2.82%", "stck_cnt": 4, "incr_cnt": 4, "flat_cnt": 0, "desc_cnt": 0},
{"cate_url": "https://finance.naver.com/sise/sise_group_detail.naver?type=upjong&no=323", "cate_name": "해운사", "vart_rate": "2.74%", "stck_cnt": 8, "incr_cnt": 7, "flat_cnt": 0, "desc_cnt": 1},
{"cate_url": "https://finance.naver.com/sise/sise_group_detail.naver?type=upjong&no=276", "cate_name": "복합기업", "vart_rate": "2.62%", "stck_cnt": 20, "incr_cnt": 19, "flat_cnt": 0, "desc_cnt": 1},
{"cate_url": "https://finance.naver.com/sise/sise_group_detail.naver?type=upjong&no=317", "cate_name": "호텔,레스토랑,레저", "vart_rate": "2.58%", "stck_cnt": 19, "incr_cnt": 19, "flat_cnt": 0, "desc_cnt": 0},
{"cate_url": "https://finance.naver.com/sise/sise_group_detail.naver?type=upjong&no=261", "cate_name": "제약", "vart_rate": "2.56%", "stck_cnt": 161, "incr_cnt": 149, "flat_cnt": 3, "desc_cnt": 9},
{"cate_url": "https://finance.naver.com/sise/sise_group_detail.naver?type=upjong&no=271", "cate_name": "레저용장비와제품", "vart_rate": "2.55%", "stck_cnt": 10, "incr_cnt": 8, "flat_cnt": 0, "desc_cnt": 2},
{"cate_url": "https://finance.naver.com/sise/sise_group_detail.naver?type=upjong&no=312", "cate_name": "가스유틸리티", "vart_rate": "2.45%", "stck_cnt": 12, "incr_cnt": 10, "flat_cnt": 0, "desc_cnt": 2},
{"cate_url": "https://finance.naver.com/sise/sise_group_detail.naver?type=upjong&no=265", "cate_name": "판매업체", "vart_rate": "2.41%", "stck_cnt": 12, "incr_cnt": 8, "flat_cnt": 3, "desc_cnt": 1},
{"cate_url": "https://finance.naver.com/sise/sise_group_detail.naver?type=upjong&no=336", "cate_name": "다각화된통신서비스", "vart_rate": "2.39%", "stck_cnt": 4, "incr_cnt": 3, "flat_cnt": 0, "desc_cnt": 1},
{"cate_url": "https://finance.naver.com/sise/sise_group_detail.naver?type=upjong&no=302", "cate_name": "식품과기본식료품소매", "vart_rate": "2.34%", "stck_cnt": 8, "incr_cnt": 6, "flat_cnt": 1, "desc_cnt": 1},
{"cate_url": "https://finance.naver.com/sise/sise_group_detail.naver?type=upjong&no=333", "cate_name": "무선통신서비스", "vart_rate": "2.27%", "stck_cnt": 4, "incr_cnt": 4, "flat_cnt": 0, "desc_cnt": 0},
{"cate_url": "https://finance.naver.com/sise/sise_group_detail.naver?type=upjong&no=334", "cate_name": "무역회사와판매업체", "vart_rate": "2.16%", "stck_cnt": 5, "incr_cnt": 5, "flat_cnt": 0, "desc_cnt": 0},
{"cate_url": "https://finance.naver.com/sise/sise_group_detail.naver?type=upjong&no=290", "cate_name": "교육서비스", "vart_rate": "2.13%", "stck_cnt": 18, "incr_cnt": 15, "flat_cnt": 1, "desc_cnt": 2},
{"cate_url": "https://finance.naver.com/sise/sise_group_detail.naver?type=upjong&no=270", "cate_name": "자동차부품", "vart_rate": "2.08%", "stck_cnt": 141, "incr_cnt": 124, "flat_cnt": 5, "desc_cnt": 12},
{"cate_url": "https://finance.naver.com/sise/sise_group_detail.naver?type=upjong&no=295", "cate_name": "에너지장비및서비스", "vart_rate": "2.01%", "stck_cnt": 22, "incr_cnt": 17, "flat_cnt": 1, "desc_cnt": 4},
{"cate_url": "https://finance.naver.com/sise/sise_group_detail.naver?type=upjong&no=298", "cate_name": "가정용기기와용품", "vart_rate": "1.96%", "stck_cnt": 24, "incr_cnt": 24, "flat_cnt": 0, "desc_cnt": 0},
{"cate_url": "https://finance.naver.com/sise/sise_group_detail.naver?type=upjong&no=278", "cate_name": "반도체와반도체장비", "vart_rate": "1.94%", "stck_cnt": 136, "incr_cnt": 124, "flat_cnt": 4, "desc_cnt": 8},
{"cate_url": "https://finance.naver.com/sise/sise_group_detail.naver?type=upjong&no=324", "cate_name": "상업서비스와공급품", "vart_rate": "1.91%", "stck_cnt": 25, "incr_cnt": 19, "flat_cnt": 3, "desc_cnt": 3},
{"cate_url": "https://finance.naver.com/sise/sise_group_detail.naver?type=upjong&no=264", "cate_name": "백화점과일반상점", "vart_rate": "1.9%", "stck_cnt": 12, "incr_cnt": 11, "flat_cnt": 1, "desc_cnt": 0},
{"cate_url": "https://finance.naver.com/sise/sise_group_detail.naver?type=upjong&no=272", "cate_name": "화학", "vart_rate": "1.88%", "stck_cnt": 114, "incr_cnt": 105, "flat_cnt": 4, "desc_cnt": 5},
{"cate_url": "https://finance.naver.com/sise/sise_group_detail.naver?type=upjong&no=322", "cate_name": "비철금속", "vart_rate": "1.79%", "stck_cnt": 39, "incr_cnt": 32, "flat_cnt": 2, "desc_cnt": 5},
{"cate_url": "https://finance.naver.com/sise/sise_group_detail.naver?type=upjong&no=319", "cate_name": "기타금융", "vart_rate": "1.75%", "stck_cnt": 8, "incr_cnt": 7, "flat_cnt": 0, "desc_cnt": 1},
{"cate_url": "https://finance.naver.com/sise/sise_group_detail.naver?type=upjong&no=329", "cate_name": "도로와철도운송", "vart_rate": "1.7%", "stck_cnt": 8, "incr_cnt": 7, "flat_cnt": 1, "desc_cnt": 0},
{"cate_url": "https://finance.naver.com/sise/sise_group_detail.naver?type=upjong&no=291", "cate_name": "조선", "vart_rate": "1.65%", "stck_cnt": 25, "incr_cnt": 22, "flat_cnt": 1, "desc_cnt": 2},
{"cate_url": "https://finance.naver.com/sise/sise_group_detail.naver?type=upjong&no=25", "cate_name": "기타", "vart_rate": "1.6%", "stck_cnt": 1051, "incr_cnt": 711, "flat_cnt": 96, "desc_cnt": 244},
{"cate_url": "https://finance.naver.com/sise/sise_group_detail.naver?type=upjong&no=318", "cate_name": "종이와목재", "vart_rate": "1.52%", "stck_cnt": 15, "incr_cnt": 12, "flat_cnt": 0, "desc_cnt": 3},
{"cate_url": "https://finance.naver.com/sise/sise_group_detail.naver?type=upjong&no=305", "cate_name": "항공사", "vart_rate": "1.3%", "stck_cnt": 10, "incr_cnt": 9, "flat_cnt": 1, "desc_cnt": 0},
{"cate_url": "https://finance.naver.com/sise/sise_group_detail.naver?type=upjong&no=330", "cate_name": "생명보험", "vart_rate": "1.3%", "stck_cnt": 7, "incr_cnt": 6, "flat_cnt": 1, "desc_cnt": 0},
{"cate_url": "https://finance.naver.com/sise/sise_group_detail.naver?type=upjong&no=283", "cate_name": "전기제품", "vart_rate": "1.27%", "stck_cnt": 50, "incr_cnt": 47, "flat_cnt": 2, "desc_cnt": 1},
{"cate_url": "https://finance.naver.com/sise/sise_group_detail.naver?type=upjong&no=273", "cate_name": "자동차", "vart_rate": "1.25%", "stck_cnt": 9, "incr_cnt": 7, "flat_cnt": 2, "desc_cnt": 0},
{"cate_url": "https://finance.naver.com/sise/sise_group_detail.naver?type=upjong&no=309", "cate_name": "음료", "vart_rate": "1.23%", "stck_cnt": 15, "incr_cnt": 14, "flat_cnt": 0, "desc_cnt": 1},
{"cate_url": "https://finance.naver.com/sise/sise_group_detail.naver?type=upjong&no=338", "cate_name": "사무용전자제품", "vart_rate": "0.95%", "stck_cnt": 1, "incr_cnt": 1, "flat_cnt": 0, "desc_cnt": 0},
{"cate_url": "https://finance.naver.com/sise/sise_group_detail.naver?type=upjong&no=327", "cate_name": "디스플레이패널", "vart_rate": "0.41%", "stck_cnt": 4, "incr_cnt": 3, "flat_cnt": 0, "desc_cnt": 1},
{"cate_url": "https://finance.naver.com/sise/sise_group_detail.naver?type=upjong&no=337", "cate_name": "카드", "vart_rate": "0.33%", "stck_cnt": 1, "incr_cnt": 1, "flat_cnt": 0, "desc_cnt": 0},
{"cate_url": "https://finance.naver.com/sise/sise_group_detail.naver?type=upjong&no=275", "cate_name": "담배", "vart_rate": "0.13%", "stck_cnt": 2, "incr_cnt": 2, "flat_cnt": 0, "desc_cnt": 0},
{"cate_url": "https://finance.naver.com/sise/sise_group_detail.naver?type=upjong&no=325", "cate_name": "전기유틸리티", "vart_rate": "-0.04%", "stck_cnt": 4, "incr_cnt": 3, "flat_cnt": 0, "desc_cnt": 1},
{"cate_url": "https://finance.naver.com/sise/sise_group_detail.naver?type=upjong&no=280", "cate_name": "부동산", "vart_rate": "-0.2%", "stck_cnt": 26, "incr_cnt": 15, "flat_cnt": 2, "desc_cnt": 9},
{"cate_url": "https://finance.naver.com/sise/sise_group_detail.naver?type=upjong&no=296", "cate_name": "운송인프라", "vart_rate": "-0.67%", "stck_cnt": 7, "incr_cnt": 6, "flat_cnt": 0, "desc_cnt": 1},
{"cate_url": "https://finance.naver.com/sise/sise_group_detail.naver?type=upjong&no=331", "cate_name": "복합유틸리티", "vart_rate": "-1.95%", "stck_cnt": 1, "incr_cnt": 0, "flat_cnt": 0, "desc_cnt": 1}
]